README.md
mapper.py
setup.py
lwe_mapper.egg-info/PKG-INFO
lwe_mapper.egg-info/SOURCES.txt
lwe_mapper.egg-info/dependency_links.txt
lwe_mapper.egg-info/top_level.txt