Metadata-Version: 2.1
Name: lwe-mapper
Version: 1.2.5
Summary: A simple URL-Scheme resolver
Home-page: https://github.com/linuxwhatelse/mapper
Author: linuxwhatelse
Author-email: info@linuxwhatelse.com
License: GPLv3
Keywords: url scheme resolver mapper
Platform: UNKNOWN
Classifier: Development Status :: 5 - Production/Stable
Classifier: Intended Audience :: Developers
Classifier: License :: OSI Approved :: GNU General Public License v3 (GPLv3)
Classifier: Operating System :: OS Independent
Classifier: Programming Language :: Python :: 2.7
Classifier: Programming Language :: Python :: 3.4
Classifier: Programming Language :: Python :: 3.5
Classifier: Programming Language :: Python :: 3.6
Classifier: Topic :: Software Development :: Libraries :: Python Modules
